<?xml version="1.0"?>
<webs>
	<web>
		<nombre>EDGAR</nombre>
		<apellido>DELGADO</apellido>
		<estado>Caracas</estado>
		<salon></salon>
		<direccion></direccion>
		<especialidad></especialidad>
		<experiencia></experiencia>
		<twitter>eadv80</twitter>
		<foto>participantes/edgar-delgado.png</foto>
	</web>
	<web>
		<nombre>EDUARDO</nombre>
		<apellido>MORALES</apellido>
		<estado>Valencia</estado>
		<salon></salon>
		<direccion></direccion>
		<especialidad></especialidad>
		<experiencia></experiencia>
		<twitter>Moraleseduardo8</twitter>
		<foto>participantes/eduar-morales.png</foto>
	</web>
	<web>
		<nombre>EFRAÍN</nombre>
		<apellido>ARTIGAS</apellido>
		<estado>Trujillo</estado>
		<salon></salon>
		<direccion></direccion>
		<especialidad></especialidad>
		<experiencia></experiencia>
		<twitter>13artigas</twitter>
		<foto>participantes/efrain-artigas.png</foto>
	</web>
	<web>
		<nombre>FRANCISCO</nombre>
		<apellido>RODRÍGUEZ</apellido>
		<estado>Falcón</estado>
		<salon></salon>
		<direccion></direccion>
		<especialidad></especialidad>
		<experiencia></experiencia>
		<twitter>Frankorock</twitter>
		<foto>participantes/francisco-rodriguez.png</foto>
	</web>
	<web>
		<nombre>LUIS</nombre>
		<apellido>COBA</apellido>
		<estado>Barcelona</estado>
		<salon></salon>
		<direccion></direccion>
		<especialidad></especialidad>
		<experiencia></experiencia>
		<twitter>omikeke</twitter>
		<foto>participantes/luis-coba.png</foto>
	</web>
	<web>
		<nombre>LUZ</nombre>
		<apellido>TOVAR</apellido>
		<estado>Falcón</estado>
		<salon></salon>
		<direccion></direccion>
		<especialidad></especialidad>
		<experiencia></experiencia>
		<twitter>luzmtb</twitter>
		<foto>participantes/luz-tovar.png</foto>
	</web>
	<web>
		<nombre>MARÍA</nombre>
		<apellido>RAMÓN</apellido>
		<estado>Puerto Ordaz</estado>
		<salon></salon>
		<direccion></direccion>
		<especialidad></especialidad>
		<experiencia></experiencia>
		<twitter>Mariaramon_p</twitter>
		<foto>participantes/maria-ramon.png</foto>
	</web>
	<web>
		<nombre>RHAIZA</nombre>
		<apellido>MARÍN</apellido>
		<estado>Porlamar</estado>
		<salon></salon>
		<direccion></direccion>
		<especialidad></especialidad>
		<experiencia></experiencia>
		<twitter>RhaizaMarin</twitter>
		<foto>participantes/rhaiza-marin.png</foto>
	</web>
	<web>
		<nombre>TEOLINDO</nombre>
		<apellido>MEDINA</apellido>
		<estado>Falcón</estado>
		<salon></salon>
		<direccion></direccion>
		<especialidad></especialidad>
		<experiencia></experiencia>
		<twitter>Theosteo</twitter>
		<foto>participantes/teolindo-medina.png</foto>
	</web>
	<web>
		<nombre>VICTOR</nombre>
		<apellido>SÁNCHEZ</apellido>
		<estado>Maracaibo</estado>
		<salon></salon>
		<direccion></direccion>
		<especialidad></especialidad>
		<experiencia></experiencia>
		<twitter>VictorAle031286</twitter>
		<foto>participantes/victor-sanchez.png</foto>
	</web>
	<web>
		<nombre>YOVANY</nombre>
		<apellido>GÓMEZ</apellido>
		<estado>Porlamar</estado>
		<salon></salon>
		<direccion></direccion>
		<especialidad></especialidad>
		<experiencia></experiencia>
		<twitter>Yovanygomez777</twitter>
		<foto>participantes/yonany-gomez.png</foto>
	</web>
</webs>